README.md
setup.py
KofiPyQtHelper/__init__.py
KofiPyQtHelper.egg-info/PKG-INFO
KofiPyQtHelper.egg-info/SOURCES.txt
KofiPyQtHelper.egg-info/dependency_links.txt
KofiPyQtHelper.egg-info/requires.txt
KofiPyQtHelper.egg-info/top_level.txt
KofiPyQtHelper/components/BaseWidget.py
KofiPyQtHelper/components/CustomGraphics.py
KofiPyQtHelper/components/FlowLayout.py
KofiPyQtHelper/components/ImageView.py
KofiPyQtHelper/components/ImageWidget.py
KofiPyQtHelper/components/ListWidget.py
KofiPyQtHelper/components/Pagination.py
KofiPyQtHelper/components/PaperWidget.py
KofiPyQtHelper/components/__init__.py
KofiPyQtHelper/enums/ColumnType.py
KofiPyQtHelper/enums/ComboboxValueType.py
KofiPyQtHelper/enums/DownloadTaskStatus.py
KofiPyQtHelper/enums/HttpEnums.py
KofiPyQtHelper/enums/SetupEnums.py
KofiPyQtHelper/enums/__init__.py
KofiPyQtHelper/models/BaseModel.py
KofiPyQtHelper/models/DownloadTask.py
KofiPyQtHelper/models/PlotModel.py
KofiPyQtHelper/models/__init__.py
KofiPyQtHelper/repositories/BaseRepository.py
KofiPyQtHelper/repositories/DownloadTaskRepository.py
KofiPyQtHelper/repositories/__init__.py
KofiPyQtHelper/services/BaseService.py
KofiPyQtHelper/services/DownloadTaskService.py
KofiPyQtHelper/services/__init__.py
KofiPyQtHelper/utils/Command.py
KofiPyQtHelper/utils/CommonHelper.py
KofiPyQtHelper/utils/DownloaderHelper.py
KofiPyQtHelper/utils/ExcelHelper.py
KofiPyQtHelper/utils/ReportlabHelper.py
KofiPyQtHelper/utils/Sqlite3Helper.py
KofiPyQtHelper/utils/Tools.py
KofiPyQtHelper/utils/UiHelper.py
KofiPyQtHelper/utils/__init__.py
KofiPyQtHelper/utils/Commands/BaseCommand.py
KofiPyQtHelper/utils/Commands/GraphCommand.py
KofiPyQtHelper/utils/Commands/HistoryCommand.py
KofiPyQtHelper/utils/Commands/PdfCommand.py
KofiPyQtHelper/utils/Commands/WidgetCommand.py
KofiPyQtHelper/utils/Commands/__init__.py
KofiPyQtHelper/utils/Ui/ComponentHelper.py
KofiPyQtHelper/utils/Ui/LayoutHelper.py
KofiPyQtHelper/utils/Ui/UiCommon.py
KofiPyQtHelper/utils/Ui/__init__.py
KofiPyQtHelper/utils/Ui/component/ListviewHelper.py
KofiPyQtHelper/utils/Ui/component/TableHelper.py
KofiPyQtHelper/utils/Ui/component/TreeHelper.py
KofiPyQtHelper/utils/Ui/component/ValueHelper.py
