Metadata-Version: 2.1
Name: KofiPyQtHelper
Version: 0.1.45
Summary: PyQt 的快速布局工具
Author: Kofi
Author-email: aliwkxqq@163.com
License: BSD License
